wordtoken/__init__.py
wordtoken/adapters.py
wordtoken/base_adapter.py
wordtoken/costs.py
wordtoken/exceptions.py
wordtoken/tokens.py
wordtoken/utils.py
wordtoken-0.1.2.dist-info/LICENSE
wordtoken-0.1.2.dist-info/METADATA
wordtoken-0.1.2.dist-info/WHEEL
wordtoken-0.1.2.dist-info/top_level.txt
wordtoken-0.1.2.dist-info/RECORD
