Metadata-Version: 2.2
Name: wordtoken
Version: 0.1.2
Summary: A unified library for interacting with LLMs, managing tokens, and estimating costs.
Home-page: https://wordtoken.com
Author: Zev Uhuru
Author-email: zev@esy.com
License: Apache 2.0
Classifier: Programming Language :: Python :: 3
Classifier: License :: OSI Approved :: Apache Software License
Classifier: Operating System :: OS Independent
Requires-Python: >=3.7
License-File: LICENSE
Requires-Dist: openai>=0.27.0
Requires-Dist: tiktoken>=0.4.0
Dynamic: author
Dynamic: author-email
Dynamic: classifier
Dynamic: description
Dynamic: description-content-type
Dynamic: home-page
Dynamic: license
Dynamic: requires-dist
Dynamic: requires-python
Dynamic: summary
